golden_eagle/__init__.py
golden_eagle/main.py
golden_eagle-1.0.6.1.dist-info/licenses/LICENSE.txt
golden_eagle-1.0.6.1.dist-info/METADATA
golden_eagle-1.0.6.1.dist-info/WHEEL
golden_eagle-1.0.6.1.dist-info/entry_points.txt
golden_eagle-1.0.6.1.dist-info/top_level.txt
golden_eagle-1.0.6.1.dist-info/RECORD
