Metadata-Version: 2.4
Name: golden_eagle
Version: 1.0.6.1
Summary: Face Recognition Console Application
Author-email: Takayuki Kamiyama <karuma.reason@gmail.com>
License: The MIT License
Classifier: Programming Language :: Python :: 3.13
License-File: LICENSE.txt
Requires-Dist: dlib
Requires-Dist: face-recognition
Requires-Dist: numpy
Requires-Dist: pydantic
Requires-Dist: opencv-python
Dynamic: license-file
